odoo/addons/loyalty_multi_gift/README.rst
odoo/addons/loyalty_multi_gift/__init__.py
odoo/addons/loyalty_multi_gift/__manifest__.py
odoo/addons/loyalty_multi_gift/i18n/es.po
odoo/addons/loyalty_multi_gift/i18n/it.po
odoo/addons/loyalty_multi_gift/i18n/loyalty_multi_gift.pot
odoo/addons/loyalty_multi_gift/models/__init__.py
odoo/addons/loyalty_multi_gift/models/loyalty_reward.py
odoo/addons/loyalty_multi_gift/readme/CONFIGURE.md
odoo/addons/loyalty_multi_gift/readme/CONTEXT.md
odoo/addons/loyalty_multi_gift/readme/CONTRIBUTORS.md
odoo/addons/loyalty_multi_gift/readme/DESCRIPTION.md
odoo/addons/loyalty_multi_gift/readme/USAGE.md
odoo/addons/loyalty_multi_gift/security/ir.model.access.csv
odoo/addons/loyalty_multi_gift/static/description/icon.png
odoo/addons/loyalty_multi_gift/static/description/index.html
odoo/addons/loyalty_multi_gift/tests/__init__.py
odoo/addons/loyalty_multi_gift/tests/test_loyalty_multi_gift_case.py
odoo/addons/loyalty_multi_gift/views/loyalty_program_views.xml
odoo/addons/loyalty_multi_gift/views/loyalty_reward_views.xml
odoo_addon_loyalty_multi_gift-18.0.1.0.0.2.dist-info/METADATA
odoo_addon_loyalty_multi_gift-18.0.1.0.0.2.dist-info/WHEEL
odoo_addon_loyalty_multi_gift-18.0.1.0.0.2.dist-info/top_level.txt
odoo_addon_loyalty_multi_gift-18.0.1.0.0.2.dist-info/RECORD
